LICENSE
README.md
setup.cfg
setup.py
PyCDArc/__init__.py
PyCDArc.egg-info/PKG-INFO
PyCDArc.egg-info/SOURCES.txt
PyCDArc.egg-info/dependency_links.txt
PyCDArc.egg-info/entry_points.txt
PyCDArc.egg-info/not-zip-safe
PyCDArc.egg-info/requires.txt
PyCDArc.egg-info/top_level.txt
PyCDArc/Components/AD_PostalAddress.py
PyCDArc/Components/Act.py
PyCDArc/Components/AssignedAuthor.py
PyCDArc/Components/AssignedCustodian.py
PyCDArc/Components/AssignedEntity.py
PyCDArc/Components/AssociatedEntity.py
PyCDArc/Components/Authenticator.py
PyCDArc/Components/Author.py
PyCDArc/Components/AuthoringDevice.py
PyCDArc/Components/Authorization.py
PyCDArc/Components/BL_Boolean.py
PyCDArc/Components/BirthPlace.py
PyCDArc/Components/CD_ConceptDescriptor.py
PyCDArc/Components/CE_CodedWithEquivalents.py
PyCDArc/Components/CS_CodedSimpleValue.py
PyCDArc/Components/CV_CodedValue.py
PyCDArc/Components/ClinicalDocument.py
PyCDArc/Components/Component1.py
PyCDArc/Components/Component2.py
PyCDArc/Components/Component3.py
PyCDArc/Components/Component4.py
PyCDArc/Components/Component5.py
PyCDArc/Components/Consent.py
PyCDArc/Components/Consumable.py
PyCDArc/Components/Criterion.py
PyCDArc/Components/Custodian.py
PyCDArc/Components/CustodianOrganization.py
PyCDArc/Components/DataEnterer.py
PyCDArc/Components/Device.py
PyCDArc/Components/DocumentRoot.py
PyCDArc/Components/DocumentationOf.py
PyCDArc/Components/ED_EncapsulatedData.py
PyCDArc/Components/EN_GenericName.py
PyCDArc/Components/EncompassingEncounter.py
PyCDArc/Components/Encounter.py
PyCDArc/Components/EncounterParticipant.py
PyCDArc/Components/Entity.py
PyCDArc/Components/Entry.py
PyCDArc/Components/EntryRelationship.py
PyCDArc/Components/ExternalAct.py
PyCDArc/Components/ExternalDocument.py
PyCDArc/Components/ExternalObservation.py
PyCDArc/Components/ExternalProcedure.py
PyCDArc/Components/Guardian.py
PyCDArc/Components/HealthCareFacility.py
PyCDArc/Components/II_InstanceIdentifier.py
PyCDArc/Components/INT_IntegerNumber.py
PyCDArc/Components/IVL_PQ_IntervalOfPhysicalQuantities.py
PyCDArc/Components/IVL_TS_IntervalOfTime.py
PyCDArc/Components/InFulfillmentOf.py
PyCDArc/Components/Informant12.py
PyCDArc/Components/InformationRecipient.py
